vsco_download/__init__.py
vsco_download/api.py
vsco_download-0.0.1.dist-info/LICENSE
vsco_download-0.0.1.dist-info/METADATA
vsco_download-0.0.1.dist-info/WHEEL
vsco_download-0.0.1.dist-info/top_level.txt
vsco_download-0.0.1.dist-info/RECORD
