Metadata-Version: 2.1
Name: vsco_download
Version: 0.0.1
Summary: A wrapper for VSCO download endpoints
Author: Lockermanwxlf
Author-email: sexyandhandsome12@gmail.com
Classifier: Programming Language :: Python :: 3
Classifier: License :: OSI Approved :: Apache Software License
Classifier: Operating System :: OS Independent
Requires-Python: >=3.6
License-File: LICENSE
Requires-Dist: requests
